Sequential_Elements/syncronous_counter/syncronous_counter.v
module synchronous_counter(clk, reset, en, clr, count);
parameter WIDTH = 3;

input clk, reset, en, clr;
output reg [WIDTH-1:0] count;

always @(posedge clk) begin
    if (reset || clr) begin
        count <= {WIDTH{1'b0}};
    end else if (en) begin
        count <= count + {{(WIDTH-1){1'b0}}, 1'b1};
    end
end

endmodule

Sequential_Elements/syncronous_counter/syncronous_counter_tb.v
`timescale 1ns / 1ps

module tb_synchronous_counter;

    // Parameters
    parameter WIDTH = 3;

    // Inputs
    reg clk;
    reg reset;
    reg en;
    reg clr;

    // Outputs
    wire [WIDTH-1:0] count;

    // Expected values and error tracking
    reg [WIDTH-1:0] expected_count;
    integer errors;
    integer i;

    // Instantiate the Unit Under Test (UUT)
    synchronous_counter #(
        .WIDTH(WIDTH)
    ) uut (
        .clk(clk),
        .reset(reset),
        .en(en),
        .clr(clr),
        .count(count)
    );

    // Clock generation (10ns period)
    initial begin
        clk = 0;
        forever #5 clk = ~clk; 
    end

    // Test sequence
    initial begin
        // Initialize Inputs
        reset = 1'b1;
        en = 1'b0;
        clr = 1'b0;
        errors = 0;
        expected_count = 0;

        // Dump waves for GTKWave/ModelSim
        $dumpfile("synchronous_counter.vcd");
        $dumpvars(0, tb_synchronous_counter);

        $display("\nStarting Synchronous Counter Testbench");
        $display(" Time(ns) | RST EN CLR | Expected | Actual | Check");
        $display("----------------------------------------------------------");

        // Test 1: Reset behavior
        @(negedge clk);
        check_output("RESET   ");

        // Test 2: Release reset, enable counting (tests wrap-around 7->0)
        reset = 1'b0;
        en = 1'b1;
        for (i = 1; i <= 8; i = i + 1) begin
            @(negedge clk);
            expected_count = (i == 8) ? 3'd0 : i[WIDTH-1:0];
            check_output("COUNT   ");
        end

        // Test 3: Clear override (clear should reset counter even if en is high)
        clr = 1'b1;
        @(negedge clk);
        expected_count = 3'd0;
        check_output("CLEAR   ");

        // Test 4: Release clear, disable enable (should hold value)
        clr = 1'b0;
        en = 1'b0;
        @(negedge clk);
        expected_count = 3'd0; 
        check_output("HOLD    ");

        // Test 5: Count a few steps, then verify reset takes priority over enable
        en = 1'b1;
        @(negedge clk); expected_count = 3'd1; check_output("COUNT1  ");
        @(negedge clk); expected_count = 3'd2; check_output("COUNT2  ");
        
        reset = 1'b1;
        @(negedge clk); expected_count = 3'd0; check_output("RST_OVR ");
        
        if (errors == 0) begin
            $display("\n[PASS] All tests passed.");
        end else begin
            $display("\n[FAIL] Total errors: %0d", errors);
        end
        
        $finish;
    end

    // Task to check output at the negative edge
    task check_output;
        input [63:0] step_name;
        begin
            if (count !== expected_count) begin
                $display("%9d |  %1b   %1b   %1b  |      %3b |    %3b | FAIL (%0s)", 
                         $time, reset, en, clr, expected_count, count, step_name);
                errors = errors + 1;
            end else begin
                $display("%9d |  %1b   %1b   %1b  |      %3b |    %3b | PASS (%0s)", 
                         $time, reset, en, clr, expected_count, count, step_name);
            end
        end
    endtask

endmodule

Sequential_Elements/syncronous_counter/synchronous_counter.vcd
$date
	Sun May 17 05:25:37 2026
$end
$version
	Icarus Verilog
$end
$timescale
	1ps
$end
$scope module tb_synchronous_counter $end
$var wire 3 ! count [2:0] $end
$var parameter 32 " WIDTH $end
$var reg 1 # clk $end
$var reg 1 $ clr $end
$var reg 1 % en $end
$var reg 3 & expected_count [2:0] $end
$var reg 1 ' reset $end
$var integer 32 ( errors [31:0] $end
$var integer 32 ) i [31:0] $end
$scope module uut $end
$var wire 1 # clk $end
$var wire 1 $ clr $end
$var wire 1 % en $end
$var wire 1 ' reset $end
$var parameter 32 * WIDTH $end
$var reg 3 + count [2:0] $end
$upscope $end
$scope task check_output $end
$var reg 64 , step_name [63:0] $end
$upscope $end
$upscope $end
$enddefinitions $end
$comment Show the parameter values. $end
$dumpall
b11 *
b11 "
$end
#0
$dumpvars
bx ,
bx +
bx )
b0 (
1'
b0 &
0%
0$
0#
bx !
$end
#5000
b0 !
b0 +
1#
#10000
b1 )
1%
0'
b101001001000101010100110100010101010100001000000010000000100000 ,
0#
#15000
b1 !
b1 +
1#
#20000
b10 )
b100001101001111010101010100111001010100001000000010000000100000 ,
b1 &
0#
#25000
b10 !
b10 +
1#
#30000
b11 )
b10 &
0#
#35000
b11 !
b11 +
1#
#40000
b100 )
b11 &
0#
#45000
b100 !
b100 +
1#
#50000
b101 )
b100 &
0#
#55000
b101 !
b101 +
1#
#60000
b110 )
b101 &
0#
#65000
b110 !
b110 +
1#
#70000
b111 )
b110 &
0#
#75000
b111 !
b111 +
1#
#80000
b1000 )
b111 &
0#
#85000
b0 !
b0 +
1#
#90000
1$
b1001 )
b0 &
0#
#95000
1#
#100000
0%
0$
b100001101001100010001010100000101010010001000000010000000100000 ,
0#
#105000
1#
#110000
1%
b100100001001111010011000100010000100000001000000010000000100000 ,
0#
#115000
b1 !
b1 +
1#
#120000
b100001101001111010101010100111001010100001100010010000000100000 ,
b1 &
0#
#125000
b10 !
b10 +
1#
#130000
1'
b100001101001111010101010100111001010100001100100010000000100000 ,
b10 &
0#
#135000
b0 !
b0 +
1#
#140000
b101001001010011010101000101111101001111010101100101001000100000 ,
b0 &
0#
